Metadata-Version: 2.1
Name: odoo10-addon-apps-download
Version: 10.0.1.0.0.99.dev15
Summary: Product Download for Appstore
Home-page: https://github.com/OCA/apps-store
Author: BizzAppDev, AgentERP, Elico Corp, Odoo Community Association (OCA)
Author-email: support@odoo-community.org
License: AGPL-3
Platform: UNKNOWN
Classifier: Programming Language :: Python
Classifier: Framework :: Odoo
Classifier: License :: OSI Approved :: GNU Affero General Public License v3
Requires-Python: ~=2.7
Requires-Dist: odoo10-addon-apps-product-creator
Requires-Dist: odoo10-addon-github-connector-odoo
Requires-Dist: odoo (<10.1dev,>=10.0)
